{"pageProps":{"filteredProjects":[{"id":1,"title":"BuildFaster","desc":"Beautiful HTML templates ready-made for your next landing page.","img":"/static/projects/buildfaster.png","link":"https://buildfaster-io.vercel.app/","tags":["HTML","CSS","Javascript","Gumroad"]},{"id":4,"title":"Create HTML Boilerplate","desc":"Generate a vanilla HTML boilerplate in a flash!","img":"/static/projects/create-html-boilerplate.png","github":"https://github.com/BraydenTW/create-html-boilerplate","tags":["Node","Javascript","NPM","HTML"]},{"id":7,"title":"Madlibs","desc":"A simple version of Madlibs built for the web!","img":"/static/projects/madlibs.png","link":"https://fillemin.netlify.app/","github":"https://github.com/braydentw/madlibs","tags":["HTML","CSS","Javascript"]}],"tag":"html"},"__N_SSG":true}